main.py
source_lever_hiring/__init__.py
source_lever_hiring/manifest.yaml
source_lever_hiring/run.py
source_lever_hiring/source.py
airbyte_source_lever_hiring-0.3.1.dist-info/METADATA
airbyte_source_lever_hiring-0.3.1.dist-info/WHEEL
airbyte_source_lever_hiring-0.3.1.dist-info/entry_points.txt
airbyte_source_lever_hiring-0.3.1.dist-info/RECORD
