Metadata-Version: 2.1
Name: airbyte-source-lever-hiring
Version: 0.3.1
Summary: Source implementation for lever-hiring.
Home-page: https://airbyte.com
License: MIT
Author: Airbyte
Author-email: contact@airbyte.io
Requires-Python: >=3.9,<3.12
Classifier: License :: OSI Approved :: MIT License
Classifier: Programming Language :: Python :: 3
Classifier: Programming Language :: Python :: 3.9
Classifier: Programming Language :: Python :: 3.10
Classifier: Programming Language :: Python :: 3.11
Requires-Dist: airbyte-cdk (>=0,<1)
Requires-Dist: responses (>=0.25.0,<0.26.0)
Project-URL: Documentation, https://docs.airbyte.com/integrations/sources/lever-hiring
Project-URL: Repository, https://github.com/airbytehq/airbyte
